CHANGELOG.md
LICENSE
MANIFEST.in
README.rst
TODO.rst
setup.py
threadactive.py
threadactive.egg-info/PKG-INFO
threadactive.egg-info/SOURCES.txt
threadactive.egg-info/dependency_links.txt
threadactive.egg-info/top_level.txt