Metadata-Version: 1.1
Name: threadactive
Version: 0.1.2
Summary: A simple utility help building multithread application through message queue
Home-page: https://github.com/sunjinopensource/threadactive/
Author: Sun Jin
Author-email: sunjinopensource@qq.com
License: UNKNOWN
Platform: UNKNOWN
Classifier: Development Status :: 3 - Alpha
Classifier: Intended Audience :: Developers
Classifier: License :: OSI Approved :: MIT License
Classifier: Operating System :: OS Independent
Classifier: Programming Language :: Python
Classifier: Programming Language :: Python :: 3
